pyparasol/__init__.py
pyparasol/html_rendering.py
pyparasol/main.py
pyparasol-1.0b2.dist-info/LICENSE
pyparasol-1.0b2.dist-info/METADATA
pyparasol-1.0b2.dist-info/WHEEL
pyparasol-1.0b2.dist-info/entry_points.txt
pyparasol-1.0b2.dist-info/top_level.txt
pyparasol-1.0b2.dist-info/RECORD
