Metadata-Version: 2.1
Name: pyparasol
Version: 1.0b2
Summary: Web-based visualization tool for hyper-parameters based on Parasol (parallel coordinates)
Home-page: https://github.com/dominikandreas/pyparasol.git
Author: Dominik Andreas
Author-email: dominikandreas@users.noreply.github.com
License: UNKNOWN
Platform: UNKNOWN
Classifier: Programming Language :: Python :: 3
Classifier: License :: OSI Approved :: MIT License
Classifier: Operating System :: OS Independent
Classifier: Development Status :: 4 - Beta
Classifier: Environment :: Console
Classifier: Intended Audience :: Science/Research
Classifier: Framework :: Flask
Classifier: Environment :: Web Environment
Classifier: Topic :: Scientific/Engineering :: Visualization
Requires-Python: >=3.6
Requires-Dist: pandas
Requires-Dist: numpy
Requires-Dist: flask
